pyrt/__init__.py
pyrt/camera/__init__.py
pyrt/camera/camera.py
pyrt/camera/orthographiccamera.py
pyrt/camera/perspectivecamera.py
pyrt/geometry/__init__.py
pyrt/geometry/bbox.py
pyrt/geometry/shape.py
pyrt/geometry/sphere.py
pyrt/geometry/triangle.py
pyrt/geometry/trianglemesh.py
pyrt/geometry/vertex.py
pyrt/light/__init__.py
pyrt/light/light.py
pyrt/light/pointlight.py
pyrt/light/spotlight.py
pyrt/material/__init__.py
pyrt/material/material.py
pyrt/material/phongmaterial.py
pyrt/math/__init__.py
pyrt/math/constants.py
pyrt/math/mat4.py
pyrt/math/matops.py
pyrt/math/ops.py
pyrt/math/perlin.py
pyrt/math/ray.py
pyrt/math/vec2.py
pyrt/math/vec3.py
pyrt/math/vec4.py
pyrt/math/vecops.py
pyrt/renderer/__init__.py
pyrt/renderer/renderer.py
pyrt/renderer/rgbimage.py
pyrt/renderer/simplert.py
pyrt/scene/__init__.py
pyrt/scene/scene.py
pyrt/utils/__init__.py
pyrt/utils/display.py
pyrt-0.5.7.dist-info/LICENSE.md
pyrt-0.5.7.dist-info/METADATA
pyrt-0.5.7.dist-info/WHEEL
pyrt-0.5.7.dist-info/top_level.txt
pyrt-0.5.7.dist-info/RECORD
